toolbrain/__init__.py
toolbrain/brain.py
toolbrain/config.py
toolbrain/core_types.py
toolbrain/factory.py
toolbrain/models.py
toolbrain/prompt.py
toolbrain/retriever.py
toolbrain/rewards.py
toolbrain/adapters/__init__.py
toolbrain/adapters/base_adapter.py
toolbrain/adapters/langchain/__init__.py
toolbrain/adapters/langchain/hf_tool_wrapper.py
toolbrain/adapters/langchain/langchain_adapter.py
toolbrain/adapters/smolagent/__init__.py
toolbrain/adapters/smolagent/smolagent_adapter.py
toolbrain/learning/__init__.py
toolbrain/learning/policy.py
toolbrain/learning/dpo/__init__.py
toolbrain/learning/dpo/algo.py
toolbrain/learning/dpo/utils.py
toolbrain/learning/grpo/__init__.py
toolbrain/learning/grpo/algo.py
toolbrain/learning/grpo/losses.py
toolbrain/learning/grpo/utils.py
toolbrain/learning/supervised/__init__.py
toolbrain/learning/supervised/algo.py
toolbrain-0.1.3.dist-info/METADATA
toolbrain-0.1.3.dist-info/WHEEL
toolbrain-0.1.3.dist-info/top_level.txt
toolbrain-0.1.3.dist-info/RECORD
