Metadata-Version: 2.4
Name: toolbrain
Version: 0.1.3
Summary: A framework for training LLM-powered agents to use tools more effectively using Reinforcement Learning
Author-email: ToolBrain Team <team@toolbrain.ai>
Project-URL: Homepage, https://github.com/toolbrain/toolbrain
Project-URL: Documentation, https://toolbrain.readthedocs.io
Project-URL: Repository, https://github.com/toolbrain/toolbrain
Project-URL: Issues, https://github.com/toolbrain/toolbrain/issues
Keywords: llm,agents,reinforcement-learning,tools,ai
Classifier: Development Status :: 3 - Alpha
Classifier: Intended Audience :: Developers
Classifier: License :: OSI Approved :: MIT License
Classifier: Programming Language :: Python :: 3
Classifier: Programming Language :: Python :: 3.10
Classifier: Programming Language :: Python :: 3.11
Classifier: Programming Language :: Python :: 3.12
Requires-Python: >=3.10
Requires-Dist: smolagents>=0.1.0
Requires-Dist: openai>=1.0.0
Requires-Dist: typing-extensions>=4.0.0
Requires-Dist: python-dotenv>=1.0.0
Requires-Dist: peft>=0.17.0
Requires-Dist: litellm
Requires-Dist: google-generativeai
Requires-Dist: gradio
Requires-Dist: datasets<4.0.0,>=3.4.1
Requires-Dist: langchain>=1.0.0a10
Requires-Dist: langchain-huggingface
Requires-Dist: langgraph
Requires-Dist: langchain_core
Requires-Dist: bitsandbytes
Provides-Extra: torch
Requires-Dist: torch; extra == "torch"
Requires-Dist: accelerate; extra == "torch"
Provides-Extra: transformers
Requires-Dist: transformers; extra == "transformers"
Requires-Dist: toolbrain[torch]; extra == "transformers"
Provides-Extra: unsloth
Requires-Dist: unsloth; extra == "unsloth"
Requires-Dist: bitsandbytes; extra == "unsloth"
Requires-Dist: xformers; extra == "unsloth"
Requires-Dist: toolbrain[transformers]; extra == "unsloth"
Provides-Extra: dev
Requires-Dist: pytest>=7.0.0; extra == "dev"
Requires-Dist: black>=22.0.0; extra == "dev"
Requires-Dist: isort>=5.0.0; extra == "dev"
Requires-Dist: mypy>=1.0.0; extra == "dev"
Provides-Extra: examples-base
Requires-Dist: pandas; extra == "examples-base"
Requires-Dist: matplotlib; extra == "examples-base"
Requires-Dist: seaborn; extra == "examples-base"
Requires-Dist: toolbrain[transformers]; extra == "examples-base"
Provides-Extra: examples-full
Requires-Dist: toolbrain[examples-base]; extra == "examples-full"
Requires-Dist: toolbrain[unsloth]; extra == "examples-full"
Provides-Extra: all
Requires-Dist: toolbrain[dev,examples-full]; extra == "all"
